num_stack_arithmac/__init__.py
num_stack_arithmac/compile.py
num_stack_arithmac-0.0.2.dist-info/METADATA
num_stack_arithmac-0.0.2.dist-info/WHEEL
num_stack_arithmac-0.0.2.dist-info/licenses/LICENSE
num_stack_arithmac-0.0.2.dist-info/RECORD
