Metadata-Version: 2.1
Name: num_stack_arithmac
Version: 0.0.2
Summary: The Num Stack Arithmac programming language.
Project-URL: Homepage, https://github.com/PlaceReporter99/Num-Stack-Arithmac/
Project-URL: Bug Tracker, https://github.com/PlaceReporter99/Num-Stack-Arithmac/issues
Author-email: PlaceReporter99 <sfurman35@outlook.com>
License-File: LICENSE
Classifier: License :: OSI Approved :: MIT License
Classifier: Operating System :: OS Independent
Classifier: Programming Language :: Python :: 3
Requires-Python: >=3.7
